gvpp/__init__.py
gvpp/__main__.py
gvpp/action.py
gvpp/animation.py
gvpp/jupyter.py
gvpp/render.py
gvpp-1.1.2.dist-info/DESCRIPTION.rst
gvpp-1.1.2.dist-info/METADATA
gvpp-1.1.2.dist-info/RECORD
gvpp-1.1.2.dist-info/WHEEL
gvpp-1.1.2.dist-info/metadata.json
gvpp-1.1.2.dist-info/top_level.txt
